{"v":"5.6.4","fr":24,"ip":0,"op":48,"w":255,"h":210,"nm":"room_guard_submarine01_lottie","ddd":0,"assets":[{"id":"image_0","w":30,"h":25,"u":"images/","p":"img_0.png","e":0},{"id":"image_1","w":60,"h":60,"u":"images/","p":"img_1.png","e":0},{"id":"image_2","w":60,"h":60,"u":"images/","p":"img_2.png","e":0},{"id":"image_3","w":70,"h":71,"u":"images/","p":"img_3.png","e":0},{"id":"image_4","w":71,"h":72,"u":"images/","p":"img_4.png","e":0},{"id":"image_5","w":77,"h":77,"u":"images/","p":"img_5.png","e":0},{"id":"image_6","w":79,"h":80,"u":"images/","p":"img_6.png","e":0},{"id":"image_7","w":9,"h":23,"u":"images/","p":"img_7.png","e":0},{"id":"image_8","w":66,"h":113,"u":"images/","p":"img_8.png","e":0},{"id":"image_9","w":61,"h":39,"u":"images/","p":"img_9.png","e":0},{"id":"image_10","w":21,"h":49,"u":"images/","p":"img_10.png","e":0},{"id":"image_11","w":43,"h":40,"u":"images/","p":"img_11.png","e":0},{"id":"image_12","w":198,"h":137,"u":"images/","p":"img_12.png","e":0},{"id":"image_13","w":59,"h":33,"u":"images/","p":"img_13.png","e":0},{"id":"image_14","w":155,"h":71,"u":"images/","p":"img_14.png","e":0},{"id":"image_15","w":17,"h":16,"u":"images/","p":"img_15.png","e":0},{"id":"image_16","w":17,"h":22,"u":"images/","p":"img_16.png","e":0},{"id":"image_17","w":75,"h":44,"u":"images/","p":"img_17.png","e":0},{"id":"comp_0","layers":[{"ddd":0,"ind":1,"ty":0,"nm":"预合成 5","td":1,"refId":"comp_1","sr":1,"ks":{"o":{"a":0,"k":100,"ix":11},"r":{"a":0,"k":0,"ix":10},"p":{"a":0,"k":[127.5,105,0],"ix":2},"a":{"a":0,"k":[127.5,105,0],"ix":1},"s":{"a":0,"k":[100,100,100],"ix":6}},"ao":0,"w":255,"h":210,"ip":0,"op":360,"st":0,"bm":0},{"ddd":0,"ind":2,"ty":2,"nm":"扫光2.png","cl":"png","tt":1,"refId":"image_14","sr":1,"ks":{"o":{"a":0,"k":40,"ix":11},"r":{"a":0,"k":104,"ix":10},"p":{"a":1,"k":[{"i":{"x":0.833,"y":0.833},"o":{"x":0.167,"y":0.167},"t":0,"s":[-69.5,105,0],"to":[64.833,0,0],"ti":[-64.833,0,0]},{"t":48,"s":[319.5,105,0]}],"ix":2},"a":{"a":0,"k":[77.5,35.5,0],"ix":1},"s":{"a":0,"k":[164.516,170.423,100],"ix":6}},"ao":0,"ip":0,"op":360,"st":0,"bm":0},{"ddd":0,"ind":3,"ty":0,"nm":"预合成 5","refId":"comp_1","sr":1,"ks":{"o":{"a":0,"k":100,"ix":11},"r":{"a":0,"k":0,"ix":10},"p":{"a":0,"k":[127.5,105,0],"ix":2},"a":{"a":0,"k":[127.5,105,0],"ix":1},"s":{"a":0,"k":[100,100,100],"ix":6}},"ao":0,"w":255,"h":210,"ip":0,"op":360,"st":0,"bm":0},{"ddd":0,"ind":4,"ty":0,"nm":"特效","refId":"comp_7","sr":1,"ks":{"o":{"a":0,"k":100,"ix":11},"r":{"a":0,"k":0,"ix":10},"p":{"a":0,"k":[127.5,105,0],"ix":2},"a":{"a":0,"k":[127.5,105,0],"ix":1},"s":{"a":0,"k":[100,100,100],"ix":6}},"ao":0,"w":255,"h":210,"ip":0,"op":360,"st":0,"bm":0}]},{"id":"comp_1","layers":[{"ddd":0,"ind":1,"ty":0,"nm":"头像框","refId":"comp_2","sr":1,"ks":{"o":{"a":0,"k":100,"ix":11},"r":{"a":0,"k":0,"ix":10},"p":{"a":0,"k":[127.5,105,0],"ix":2},"a":{"a":0,"k":[127.5,105,0],"ix":1},"s":{"a":0,"k":[100,100,100],"ix":6}},"ao":0,"w":255,"h":210,"ip":0,"op":360,"st":0,"bm":0},{"ddd":0,"ind":2,"ty":2,"nm":"尾部","refId":"image_7","sr":1,"ks":{"o":{"a":0,"k":100,"ix":11},"r":{"a":0,"k":0,"ix":10},"p":{"a":0,"k":[233.5,125.5,0],"ix":2},"a":{"a":0,"k":[4.5,11.5,0],"ix":1},"s":{"a":0,"k":[100,100,100],"ix":6}},"ao":0,"ip":0,"op":360,"st":0,"bm":0},{"ddd":0,"ind":3,"ty":0,"nm":"组 1 拷贝","refId":"comp_5","sr":1,"ks":{"o":{"a":0,"k":100,"ix":11},"r":{"a":0,"k":0,"ix":10},"p":{"a":0,"k":[231.611,126.233,0],"ix":2},"a":{"a":0,"k":[60,60,0],"ix":1},"s":{"a":0,"k":[15.84,87.532,100],"ix":6}},"ao":0,"w":120,"h":120,"ip":0,"op":360,"st":0,"bm":0},{"ddd":0,"ind":4,"ty":0,"nm":"主体","refId":"comp_6","sr":1,"ks":{"o":{"a":0,"k":100,"ix":11},"r":{"a":0,"k":0,"ix":10},"p":{"a":0,"k":[127.5,105,0],"ix":2},"a":{"a":0,"k":[127.5,105,0],"ix":1},"s":{"a":0,"k":[100,100,100],"ix":6}},"ao":0,"w":255,"h":210,"ip":0,"op":360,"st":0,"bm":0}]},{"id":"comp_2","layers":[{"ddd":0,"ind":1,"ty":2,"nm":"组 28","refId":"image_0","sr":1,"ks":{"o":{"a":0,"k":100,"ix":11},"r":{"a":0,"k":0,"ix":10},"p":{"a":0,"k":[133,123.5,0],"ix":2},"a":{"a":0,"k":[15,12.5,0],"ix":1},"s":{"a":0,"k":[100,100,100],"ix":6}},"ao":0,"ip":0,"op":360,"st":0,"bm":0},{"ddd":0,"ind":2,"ty":0,"nm":"右","refId":"comp_3","sr":1,"ks":{"o":{"a":0,"k":100,"ix":11},"r":{"a":0,"k":0,"ix":10},"p":{"a":0,"k":[127.5,105,0],"ix":2},"a":{"a":0,"k":[127.5,105,0],"ix":1},"s":{"a":0,"k":[100,100,100],"ix":6}},"ao":0,"w":255,"h":210,"ip":0,"op":360,"st":0,"bm":0},{"ddd":0,"ind":3,"ty":0,"nm":"左","refId":"comp_4","sr":1,"ks":{"o":{"a":0,"k":100,"ix":11},"r":{"a":0,"k":0,"ix":10},"p":{"a":0,"k":[127.5,105,0],"ix":2},"a":{"a":0,"k":[127.5,105,0],"ix":1},"s":{"a":0,"k":[100,100,100],"ix":6}},"ao":0,"w":255,"h":210,"ip":0,"op":360,"st":0,"bm":0}]},{"id":"comp_3","layers":[{"ddd":0,"ind":1,"ty":2,"nm":"组 29","refId":"image_3","sr":1,"ks":{"o":{"a":0,"k":100,"ix":11},"r":{"a":0,"k":0,"ix":10},"p":{"a":0,"k":[170,123.5,0],"ix":2},"a":{"a":0,"k":[35,35.5,0],"ix":1},"s":{"a":0,"k":[100,100,100],"ix":6}},"ao":0,"ip":0,"op":360,"st":0,"bm":0},{"ddd":0,"ind":2,"ty":2,"nm":"img_2.png","cl":"png","refId":"image_2","sr":1,"ks":{"o":{"a":0,"k":100,"ix":11},"r":{"a":0,"k":0,"ix":10},"p":{"a":0,"k":[170.625,123.375,0],"ix":2},"a":{"a":0,"k":[30,30,0],"ix":1},"s":{"a":0,"k":[107.5,107.5,100],"ix":6}},"ao":0,"ip":0,"op":360,"st":0,"bm":0},{"ddd":0,"ind":4,"ty":2,"nm":"组 30","refId":"image_4","sr":1,"ks":{"o":{"a":0,"k":100,"ix":11},"r":{"a":0,"k":0,"ix":10},"p":{"a":0,"k":[171.5,124,0],"ix":2},"a":{"a":0,"k":[35.5,36,0],"ix":1},"s":{"a":0,"k":[100,100,100],"ix":6}},"ao":0,"ip":0,"op":360,"st":0,"bm":0}]},{"id":"comp_4","layers":[{"ddd":0,"ind":1,"ty":2,"nm":"组 31","refId":"image_5","sr":1,"ks":{"o":{"a":0,"k":100,"ix":11},"r":{"a":0,"k":0,"ix":10},"p":{"a":0,"k":[92.5,122.5,0],"ix":2},"a":{"a":0,"k":[38.5,38.5,0],"ix":1},"s":{"a":0,"k":[100,100,100],"ix":6}},"ao":0,"ip":0,"op":360,"st":0,"bm":0},{"ddd":0,"ind":2,"ty":2,"nm":"img_1.png","cl":"png","refId":"image_1","sr":1,"ks":{"o":{"a":0,"k":100,"ix":11},"r":{"a":0,"k":0,"ix":10},"p":{"a":0,"k":[92.363,122.875,0],"ix":2},"a":{"a":0,"k":[30,30,0],"ix":1},"s":{"a":0,"k":[118.333,118.333,100],"ix":6}},"ao":0,"ip":0,"op":360,"st":0,"bm":0},{"ddd":0,"ind":3,"ty":2,"nm":"组 32","refId":"image_6","sr":1,"ks":{"o":{"a":0,"k":100,"ix":11},"r":{"a":0,"k":0,"ix":10},"p":{"a":0,"k":[93.5,124,0],"ix":2},"a":{"a":0,"k":[39.5,40,0],"ix":1},"s":{"a":0,"k":[100,100,100],"ix":6}},"ao":0,"ip":0,"op":360,"st":0,"bm":0}]},{"id":"comp_5","layers":[{"ddd":0,"ind":1,"ty":2,"nm":"组 1 拷贝/守护初级的255.psd","cl":"psd","refId":"image_8","sr":1,"ks":{"o":{"a":0,"k":100,"ix":11},"r":{"a":1,"k":[{"i":{"x":[0.833],"y":[0.833]},"o":{"x":[0.167],"y":[0.167]},"t":0,"s":[0]},{"t":48,"s":[720]}],"ix":10},"p":{"a":0,"k":[60,60,0],"ix":2},"a":{"a":0,"k":[33,56.5,0],"ix":1},"s":{"a":0,"k":[100,100,100],"ix":6}},"ao":0,"ip":0,"op":360,"st":0,"bm":0}]},{"id":"comp_6","layers":[{"ddd":0,"ind":1,"ty":2,"nm":"组 13","refId":"image_9","sr":1,"ks":{"o":{"a":0,"k":100,"ix":11},"r":{"a":0,"k":0,"ix":10},"p":{"a":0,"k":[153.5,179.5,0],"ix":2},"a":{"a":0,"k":[30.5,19.5,0],"ix":1},"s":{"a":0,"k":[100,100,100],"ix":6}},"ao":0,"ip":0,"op":360,"st":0,"bm":0},{"ddd":0,"ind":2,"ty":2,"nm":"组 14","refId":"image_10","sr":1,"ks":{"o":{"a":0,"k":100,"ix":11},"r":{"a":0,"k":0,"ix":10},"p":{"a":0,"k":[221.5,125.5,0],"ix":2},"a":{"a":0,"k":[10.5,24.5,0],"ix":1},"s":{"a":0,"k":[100,100,100],"ix":6}},"ao":0,"ip":0,"op":360,"st":0,"bm":0},{"ddd":0,"ind":3,"ty":2,"nm":"组 10","refId":"image_11","sr":1,"ks":{"o":{"a":0,"k":100,"ix":11},"r":{"a":0,"k":0,"ix":10},"p":{"a":0,"k":[104.5,39,0],"ix":2},"a":{"a":0,"k":[21.5,20,0],"ix":1},"s":{"a":0,"k":[100,100,100],"ix":6}},"ao":0,"ip":0,"op":360,"st":0,"bm":0},{"ddd":0,"ind":5,"ty":2,"nm":"组 15","refId":"image_12","sr":1,"ks":{"o":{"a":0,"k":100,"ix":11},"r":{"a":0,"k":0,"ix":10},"p":{"a":0,"k":[120,119.5,0],"ix":2},"a":{"a":0,"k":[99,68.5,0],"ix":1},"s":{"a":0,"k":[100,100,100],"ix":6}},"ao":0,"ip":0,"op":360,"st":0,"bm":0},{"ddd":0,"ind":6,"ty":2,"nm":"图层 429","refId":"image_13","sr":1,"ks":{"o":{"a":0,"k":100,"ix":11},"r":{"a":0,"k":0,"ix":10},"p":{"a":0,"k":[183.5,159.5,0],"ix":2},"a":{"a":0,"k":[29.5,16.5,0],"ix":1},"s":{"a":0,"k":[100,100,100],"ix":6}},"ao":0,"ip":0,"op":360,"st":0,"bm":0}]},{"id":"comp_7","layers":[{"ddd":0,"ind":3,"ty":2,"nm":"组 23","refId":"image_15","sr":1,"ks":{"o":{"a":1,"k":[{"i":{"x":[0.833],"y":[0.833]},"o":{"x":[0.167],"y":[0.167]},"t":0,"s":[0]},{"i":{"x":[0.833],"y":[0.833]},"o":{"x":[0.167],"y":[0.167]},"t":12,"s":[100]},{"i":{"x":[0.833],"y":[0.833]},"o":{"x":[0.167],"y":[0.167]},"t":36,"s":[100]},{"t":48,"s":[0]}],"ix":11},"r":{"a":1,"k":[{"i":{"x":[0.833],"y":[0.833]},"o":{"x":[0.167],"y":[0.167]},"t":0,"s":[0]},{"t":48,"s":[-95]}],"ix":10},"p":{"a":1,"k":[{"i":{"x":0.833,"y":0.833},"o":{"x":0.167,"y":0.167},"t":0,"s":[84.375,26.375,0],"to":[-5.292,1.021,0],"ti":[5.292,-1.021,0]},{"t":48,"s":[52.625,32.5,0]}],"ix":2},"a":{"a":0,"k":[8.5,8,0],"ix":1},"s":{"a":1,"k":[{"i":{"x":[0.833,0.833,0.833],"y":[0.833,0.833,0.833]},"o":{"x":[0.167,0.167,0.167],"y":[0.167,0.167,0.167]},"t":0,"s":[100,100,100]},{"t":48,"s":[61,61,100]}],"ix":6}},"ao":0,"ip":0,"op":360,"st":0,"bm":0},{"ddd":0,"ind":4,"ty":2,"nm":"组 17","refId":"image_16","sr":1,"ks":{"o":{"a":1,"k":[{"i":{"x":[0.833],"y":[0.833]},"o":{"x":[0.167],"y":[0.167]},"t":0,"s":[0]},{"i":{"x":[0.833],"y":[0.833]},"o":{"x":[0.167],"y":[0.167]},"t":12,"s":[100]},{"i":{"x":[0.833],"y":[0.833]},"o":{"x":[0.167],"y":[0.167]},"t":36,"s":[100]},{"t":48,"s":[0]}],"ix":11},"r":{"a":0,"k":0,"ix":10},"p":{"a":1,"k":[{"i":{"x":0.833,"y":0.833},"o":{"x":0.167,"y":0.167},"t":0,"s":[79.875,27.125,0],"to":[-5.083,-1.229,0],"ti":[5.083,1.229,0]},{"t":48,"s":[49.375,19.75,0]}],"ix":2},"a":{"a":0,"k":[8.5,11,0],"ix":1},"s":{"a":1,"k":[{"i":{"x":[0.833,0.833,0.833],"y":[0.833,0.833,0.833]},"o":{"x":[0.167,0.167,0.167],"y":[0.167,0.167,0.167]},"t":0,"s":[100,100,100]},{"t":48,"s":[25,25,100]}],"ix":6}},"ao":0,"ip":0,"op":360,"st":0,"bm":0},{"ddd":0,"ind":6,"ty":2,"nm":"组 20","refId":"image_17","sr":1,"ks":{"o":{"a":0,"k":100,"ix":11},"r":{"a":0,"k":0,"ix":10},"p":{"a":0,"k":[94.905,28.931,0],"ix":2},"a":{"a":0,"k":[74.905,20.931,0],"ix":1},"s":{"a":1,"k":[{"i":{"x":[0.667,0.667,0.667],"y":[1,1,1]},"o":{"x":[0.333,0.333,0.333],"y":[0,0,0]},"t":0,"s":[73.299,62.612,100]},{"i":{"x":[0.667,0.667,0.667],"y":[1,1,1]},"o":{"x":[0.333,0.333,0.333],"y":[0,0,0]},"t":24,"s":[126.033,121.674,100]},{"t":48,"s":[73.299,62.612,100]}],"ix":6}},"ao":0,"ip":0,"op":360,"st":0,"bm":0}]}],"layers":[{"ddd":0,"ind":1,"ty":2,"nm":"组 28","refId":"image_0","sr":1,"ks":{"o":{"a":0,"k":0,"ix":11},"r":{"a":0,"k":0,"ix":10},"p":{"a":0,"k":[133,123.5,0],"ix":2},"a":{"a":0,"k":[15,12.5,0],"ix":1},"s":{"a":0,"k":[100,100,100],"ix":6}},"ao":0,"ip":0,"op":360,"st":0,"bm":0},{"ddd":0,"ind":2,"ty":2,"nm":"img_1.png","cl":"png","refId":"image_1","sr":1,"ks":{"o":{"a":0,"k":0,"ix":11},"r":{"a":0,"k":0,"ix":10},"p":{"a":0,"k":[127.5,105,0],"ix":2},"a":{"a":0,"k":[30,30,0],"ix":1},"s":{"a":0,"k":[100,100,100],"ix":6}},"ao":0,"ip":0,"op":360,"st":0,"bm":0},{"ddd":0,"ind":3,"ty":2,"nm":"img_2.png","cl":"png","refId":"image_2","sr":1,"ks":{"o":{"a":0,"k":0,"ix":11},"r":{"a":0,"k":0,"ix":10},"p":{"a":0,"k":[127.5,105,0],"ix":2},"a":{"a":0,"k":[30,30,0],"ix":1},"s":{"a":0,"k":[100,100,100],"ix":6}},"ao":0,"ip":0,"op":360,"st":0,"bm":0},{"ddd":0,"ind":4,"ty":0,"nm":"守护初级的255","refId":"comp_0","sr":1,"ks":{"o":{"a":0,"k":100,"ix":11},"r":{"a":0,"k":0,"ix":10},"p":{"a":1,"k":[{"i":{"x":0.667,"y":1},"o":{"x":0.333,"y":0},"t":0,"s":[127.5,102.5,0],"to":[0,1.833,0],"ti":[0,0,0]},{"i":{"x":0.667,"y":1},"o":{"x":0.333,"y":0},"t":24,"s":[127.5,113.5,0],"to":[0,0,0],"ti":[0,1.833,0]},{"t":48,"s":[127.5,102.5,0]}],"ix":2},"a":{"a":0,"k":[127.5,105,0],"ix":1},"s":{"a":0,"k":[90,90,100],"ix":6}},"ao":0,"w":255,"h":210,"ip":0,"op":360,"st":0,"bm":0}],"markers":[]}